shooker/__init__.py
shooker/__main__.py
shooker/internal/asm.py
shooker/internal/cmpl.py
shooker/internal/ftb.py
shooker/internal/inj.py
shooker/internal/other.py
shooker-1.3.dist-info/METADATA
shooker-1.3.dist-info/WHEEL
shooker-1.3.dist-info/entry_points.txt
shooker-1.3.dist-info/licenses/LICENSE.md
shooker-1.3.dist-info/RECORD
