Metadata-Version: 2.1
Name: shooker
Version: 1.3
Summary: Tool for C-code injections in already compiled bins
Project-URL: Homepage, https://github.com/ReKreker/shooker
Project-URL: Bug Tracker, https://github.com/ReKreker/shooker/issues
Author: ReKreker
License-File: LICENSE.md
Classifier: License :: OSI Approved :: MIT License
Classifier: Programming Language :: Python :: 3
Requires-Python: >=3.5
Requires-Dist: capstone~=4.0.2
Requires-Dist: lief~=0.12.2
